<?xml version="1.0" encoding="UTF-8"?>
<entry xmlns:functx="http://www.functx.com" xmlns="http://www.tei-c.org/ns/1.0" xml:id="entry_daw"
    xml:lang="os">
    <form xml:lang="os-x-iron" type="lemma"><orth>daw</orth></form>
    <form xml:lang="os-x-digor" type="dialectal"><orth>dawæ</orth></form>
    <sense><sense><cit type="translation" xml:lang="ru">
                <q>обвинение</q>
            </cit><cit type="translation" xml:lang="en">
                <q>accusation</q>
            </cit></sense><sense><cit type="translation" xml:lang="ru">
                <q>подозрение</q>
            </cit><cit type="translation" xml:lang="en">
                <q>suspicion</q>
            </cit></sense><sense><cit type="translation" xml:lang="ru">
                <q>тяжба</q>
            </cit><cit type="translation" xml:lang="en">
                <q>lawsuit</q>
            </cit></sense></sense>
    <re><form type="lemma"><orth>daw kænyn</orth></form><sense><cit type="translation" xml:lang="ru">
                <q>возводить на кого-либо обвинение</q>
            </cit><cit type="translation" xml:lang="en">
                <q>accuse smb</q>
            </cit></sense></re>
    <re><form type="lemma"><orth>dajwag</orth></form><sense><sense><cit type="translation"
                    xml:lang="ru">
                    <q>спорный</q>
                </cit><cit type="translation" xml:lang="en">
                    <q>disputable</q>
                </cit></sense><sense><cit type="translation" xml:lang="ru">
                    <q>предмет тяжбы</q>
                </cit><cit type="translation" xml:lang="en">
                    <q>subject of litigation</q>
                </cit></sense></sense></re>
    <re><form xml:lang="os-x-iron" type="lemma"><orth>ænædaw</orth></form><form
            xml:lang="os-x-digor" type="dialectal"><orth>ædæwagæ</orth></form><sense><sense><cit
                    type="translation" xml:lang="ru">
                    <q>бесспорный</q>
                </cit><cit type="translation" xml:lang="en">
                    <q>doubtless</q>
                </cit></sense><sense><cit type="translation" xml:lang="ru">
                    <q>вне подозрения</q>
                </cit><cit type="translation" xml:lang="en">
                    <q>above suspicion</q>
                </cit></sense></sense></re>
    <cit type="exampleGroup">
        <cit type="example">
            <quote>syxag læppujyl daw kodtoj, fælæ jæm zylynæj nīcy ssardtoj</quote>
            <cit type="translation" xml:lang="ru">
                <q>подозревали соседского юношу, но не нашли против него никаких улик</q>
            </cit>
            <cit type="translation" xml:lang="en">
                <q>neighbor's young man was suspected, but no evidence was found against him</q>
            </cit>
            <bibl><ref target="#src_Сека"/><biblScope>128</biblScope></bibl>
        </cit>
        <cit type="example">
            <quote>dawæj læǵy næ mardæ ū</quote>
            <cit type="translation" xml:lang="ru">
                <q>по (одному) обвинению не убивают человека</q>
            </cit>
            <cit type="translation" xml:lang="en">
                <q>a man should not be killed due to one accusation</q>
            </cit>
            <bibl><ref target="#src_Сл."/></bibl>
        </cit>
        <cit type="example" xml:lang="os-x-digor">
            <usg type="dialect"><lang/></usg>
            <quote>ænædawæ æ kondæj</quote>
            <cit type="translation" xml:lang="ru">
                <q>она безупречна по своему сложению</q>
            </cit>
            <cit type="translation" xml:lang="en">
                <q>her figure is flawless</q>
            </cit>
            <bibl><ref target="#src_Gurdž._Wadž."/><biblScope>33</biblScope></bibl>
        </cit>
        <cit type="example" xml:lang="os-x-digor">
            <usg type="dialect"><lang/></usg>
            <quote>(ʒikkotæ) ænædawæ fedawuncæ</quote>
            <cit type="translation" xml:lang="ru">
                <q>(косы) красуются безупречные</q>
            </cit>
            <cit type="translation" xml:lang="en">
                <q>(braids) stand out flawless</q>
            </cit>
            <bibl><ref target="#src_Iræf"/><biblScope>41</biblScope></bibl>
        </cit>
    </cit>
    <cit type="exampleGroup">
        <cit type="example">
            <quote>syxag læppujyl daw kodtoj, fælæ jæm zylynæj nīcy ssardtoj</quote>
            <cit type="translation" xml:lang="ru">
                <q>подозревали соседского юношу, но не нашли против него никаких улик</q>
            </cit>
            <cit type="translation" xml:lang="en">
                <q>neighbor's young man was suspected, but no evidence was found against him</q>
            </cit>
            <bibl><ref target="#src_Сека"/><biblScope>128</biblScope></bibl>
        </cit>
        <cit type="example">
            <quote>dawæj læǵy næ mardæ ū</quote>
            <cit type="translation" xml:lang="ru">
                <q>по (одному) обвинению не убивают человека</q>
            </cit>
            <cit type="translation" xml:lang="en">
                <q>a man should not be killed due to one accusation</q>
            </cit>
            <bibl><ref target="#src_Сл."/></bibl>
        </cit>
        <cit type="example" xml:lang="os-x-digor">
            <usg type="dialect"><lang/></usg>
            <quote>ænædawæ æ kondæj</quote>
            <cit type="translation" xml:lang="ru">
                <q>она безупречна по своему сложению</q>
            </cit>
            <cit type="translation" xml:lang="en">
                <q>her figure is flawless</q>
            </cit>
            <bibl><ref target="#src_Gurdž._Wadž."/><biblScope>33</biblScope></bibl>
        </cit>
        <cit type="example" xml:lang="os-x-digor">
            <usg type="dialect"><lang/></usg>
            <quote>(ʒikkotæ) ænædawæ fedawuncæ</quote>
            <cit type="translation" xml:lang="ru">
                <q>(косы) красуются безупречные</q>
            </cit>
            <cit type="translation" xml:lang="en">
                <q>(braids) stand out flawless</q>
            </cit>
            <bibl><ref target="#src_Iræf"/><biblScope>41</biblScope></bibl>
        </cit>
    </cit>
    <etym xml:lang="ru">Из <mentioned xml:lang=""
            ><lang/><w>daʽvā</w><gloss><q>спор</q></gloss></mentioned><mentioned xml:lang=""
                    ><w/><gloss><q>тяжба</q></gloss></mentioned>, <mentioned xml:lang=""
                    ><w/><gloss><q>иск</q></gloss></mentioned>, , <mentioned xml:lang="fa"
                ><lang/><w>daʽvā kardan</w><gloss><q>заводить тяжбу с
            кем-либо</q></gloss></mentioned>, <mentioned xml:lang="tr"
                    ><lang/><w>dava</w><gloss><q>тяжба</q></gloss></mentioned><mentioned
            xml:lang="tr"><w>dava etmek</w><gloss><q>подавать иск</q></gloss></mentioned>, . Широко
        распространилось в кавказских языках: <mentioned xml:lang="lez"
            ><lang/><w>davè</w></mentioned>, <mentioned xml:lang="av"
            ><lang/><w>da%bh%bba</w></mentioned>, <mentioned xml:lang="lbe"
                    ><lang/><w>da%bh%bbi</w><gloss><q>тяжба</q></gloss></mentioned><mentioned
            xml:lang="lbe"><w/><gloss><q>спор</q></gloss></mentioned>, , <mentioned xml:lang="ce"
                ><lang/><w>dav</w></mentioned>, <mentioned xml:lang="inh"
                    ><lang/><w>dov</w><gloss><q>тяжба</q></gloss></mentioned><mentioned
            xml:lang="inh"><w/><gloss><q>вражда</q></gloss></mentioned>, , <mentioned xml:lang="kbd"
                ><lang/><w>dawā</w><gloss><q>спор</q></gloss></mentioned><mentioned xml:lang="kbd"
                    ><w/><gloss><q>тяжба</q></gloss></mentioned>, , <mentioned xml:lang="ka"
                ><lang/><w>dava</w><gloss><q>спор</q></gloss></mentioned><mentioned xml:lang="ka"
                    ><w/><gloss><q>иск</q></gloss></mentioned>, , <mentioned xml:lang="sva"
                ><lang/><w>lidev</w><gloss><q>спор</q></gloss></mentioned> и др. Ошибочные
        этимологии у Вс. %sМиллера%s [<bibl><ref target="#ref_Вс._Миллер._ОЭ"/><biblScope>III
                151</biblScope></bibl> (← <mentioned xml:lang="ae"
                    ><lang/><w>davi</w><gloss><q>обман</q></gloss></mentioned><mentioned
            xml:lang="ae"><w>dava-</w><gloss><q>обманчивый</q></gloss></mentioned>, )] и
        %sHübschmann%s’ а [<bibl><ref target="#ref_Hübschmann._Oss."
            /><biblScope>34</biblScope></bibl> (<mentioned xml:lang="sa"
                    ><lang/><w>dvaya-</w><gloss><q>двойственный</q></gloss></mentioned><mentioned
            xml:lang="sa"><w/><gloss><q>лживый</q></gloss></mentioned>, , <mentioned xml:lang="got"
                ><lang/><w>tveifls</w></mentioned>].</etym>
    <etym xml:lang="en">From <mentioned xml:lang=""
            ><lang/><w>daʽvā</w><gloss><q>dispute</q></gloss></mentioned><mentioned xml:lang=""
                    ><w/><gloss><q>lawsuit</q></gloss></mentioned>, <mentioned xml:lang=""
                    ><w/><gloss><q>suit</q></gloss></mentioned>, , <mentioned xml:lang="fa"
                ><lang/><w>daʽvā kardan</w><gloss><q>start a lawsuit process with
            smb</q></gloss></mentioned>, <mentioned xml:lang="tr"
                    ><lang/><w>dava</w><gloss><q>lawsuit</q></gloss></mentioned><mentioned
            xml:lang="tr"><w>dava etmek</w><gloss><q>register a claim</q></gloss></mentioned>, . The
        word is widespread in Caucasian languages: <mentioned xml:lang="lez"
            ><lang/><w>davè</w></mentioned>, <mentioned xml:lang="av"
            ><lang/><w>da%bh%bba</w></mentioned>, <mentioned xml:lang="lbe"
                    ><lang/><w>da%bh%bbi</w><gloss><q>lawsuit</q></gloss></mentioned><mentioned
            xml:lang="lbe"><w/><gloss><q>спор</q></gloss></mentioned>, , <mentioned xml:lang="ce"
                ><lang/><w>dav</w></mentioned>, <mentioned xml:lang="inh"
                    ><lang/><w>dov</w><gloss><q>lawsuit</q></gloss></mentioned><mentioned
            xml:lang="inh"><w/><gloss><q>hostility</q></gloss></mentioned>, , <mentioned
            xml:lang="kbd"><lang/><w>dawā</w><gloss><q>dispute</q></gloss></mentioned><mentioned
            xml:lang="kbd"><w/><gloss><q>lawsuit</q></gloss></mentioned>, , <mentioned xml:lang="ka"
                ><lang/><w>dava</w><gloss><q>dispute</q></gloss></mentioned><mentioned xml:lang="ka"
                    ><w/><gloss><q>claim</q></gloss></mentioned>, , <mentioned xml:lang="sva"
                ><lang/><w>lidev</w><gloss><q>dispute</q></gloss></mentioned> etc. Ws. %sMiller%s's
        etymology [<bibl><ref target="#ref_Вс._Миллер._ОЭ"/><biblScope>III 151</biblScope></bibl> (←
            <mentioned xml:lang="ae"
            ><lang/><w>davi</w><gloss><q>betray</q></gloss></mentioned><mentioned xml:lang="ae"
                ><w>dava-</w><gloss><q>deceptive</q></gloss></mentioned>, )] and %sHübschmann%s’s
        one [<bibl><ref target="#ref_Hübschmann._Oss."/><biblScope>34</biblScope></bibl> (<mentioned
            xml:lang="sa"><lang/><w>dvaya-</w><gloss><q>double</q></gloss></mentioned><mentioned
            xml:lang="sa"><w/><gloss><q>false</q></gloss></mentioned>, , <mentioned xml:lang="got"
                ><lang/><w>tveifls</w></mentioned>] are wrong.</etym>
</entry>
