<?xml version="1.0" encoding="UTF-8"?>
<entry xmlns:functx="http://www.functx.com" xmlns="http://www.tei-c.org/ns/1.0" xml:id="entry_æftyn"
    xml:lang="os">
    <form xml:lang="os-x-iron" type="lemma"><orth>æftyn</orth><form type="inflected" subtype="ptcp"
                ><orth>æftyd</orth></form></form>
    <form xml:lang="os-x-digor" type="dialectal"><orth>æftujun</orth><form type="inflected"
            subtype="ptcp"><orth>æftud</orth></form></form>
    <sense n="1" xml:id="sense_æftyn.1"><sense><cit type="translation" xml:lang="ru">
                <q>падать</q>
            </cit><cit type="translation" xml:lang="en">
                <q>to fall</q>
            </cit></sense><sense><cit type="translation" xml:lang="ru">
                <q>заходить (о солнце)</q>
            </cit><cit type="translation" xml:lang="en">
                <q>to set (of sun)</q>
            </cit></sense></sense>
    <sense n="2" xml:id="sense_æftyn.2"><cit type="translation" xml:lang="ru">
            <q>попадать</q>
        </cit><cit type="translation" xml:lang="en">
            <q>to appear at some place</q>
        </cit></sense>
    <sense n="3" xml:id="sense_æftyn.3"><cit type="translation" xml:lang="ru">
            <q>прибавляться</q>
        </cit><cit type="translation" xml:lang="en">
            <q>to be added</q>
        </cit></sense>
    <cit type="exampleGroup">
        <cit type="example">
            <quote>kæfync … dyværccygæj; binægtæ sqær kænync „æræftʒystut“, wællægtæ sæm ærʒūrync
                „ne ’ræftʒystæm“</quote>
            <cit type="translation" xml:lang="ru">
                <q>пляшут в два яруса (т. е. одни на плечах других); нижние кричат (верхним): «вы
                    свалитесь»; верхние им говорят: «не свалимся»</q>
            </cit>
            <cit type="translation" xml:lang="en">
                <q>they are dancing at two levels (ones at the shoulders of others); the ones below
                    are shouting (to the ones above): “you will fall”; the ones above tell them: “we
                    won't fall”</q>
            </cit>
            <bibl><ref target="#src_Čerm."/><biblScope>97</biblScope></bibl>
        </cit>
        <cit type="example">
            <quote>rarynḱyn qyzty; qæmpyl nyffældæxt, nyftyd</quote>
            <cit type="translation" xml:lang="ru">
                <q>он заболел в стужу; повалился, упал на солому</q>
            </cit>
            <cit type="translation" xml:lang="en">
                <q>he fell ill in the cold; fell down, fell on the straw</q>
            </cit>
            <bibl><ref target="#src_Niger"/><biblScope>68</biblScope></bibl>
        </cit>
        <cit type="example">
            <quote>nyxasy æftydæj læwwydysty</quote>
            <cit type="translation" xml:lang="ru">
                <q>они лежали повалившись на нихасе</q>
            </cit>
            <cit type="translation" xml:lang="en">
                <q>they were lying at the nihas</q>
            </cit>
            <bibl><ref target="#src_ОТ"/><biblScope>71</biblScope></bibl>
        </cit>
        <cit type="example" xml:lang="os-x-digor">
            <usg type="dialect"><lang/></usg>
            <quote>baftudæj k’os dær doni æxsæni</quote>
            <cit type="translation" xml:lang="ru">
                <q>чаша упала в середину реки</q>
            </cit>
            <cit type="translation" xml:lang="en">
                <q>the bowl fell into the middle of the river</q>
            </cit>
            <bibl><ref target="#src_Bes."/><biblScope>110</biblScope></bibl>
        </cit>
        <cit type="example" xml:lang="os-x-digor">
            <usg type="dialect"><lang/></usg>
            <quote>xor raftudæj</quote>
            <cit type="translation" xml:lang="ru">
                <q>солнце зашло</q>
            </cit>
            <cit type="translation" xml:lang="en">
                <q>the sun went down</q>
            </cit>
        </cit>
        <cit type="example" xml:lang="os-x-digor">
            <usg type="dialect"><lang/></usg>
            <quote>kæd dæ bæxbæl cal ardoi es, wal zildi ærkænaj xor-æftudmæ
                ʒaxan-maxan-bæl...</quote>
            <cit type="translation" xml:lang="ru">
                <q>если ты столько раз обернешься до захода солнца по аду, сколько волос на твоем
                    коне...</q>
            </cit>
            <cit type="translation" xml:lang="en">
                <q>if you turn around in hell before the sun goes down as many times as many hairs
                    your horse has...</q>
            </cit>
            <bibl><ref target="#src_Диг._сказ."/><biblScope>38</biblScope></bibl>
        </cit>
        <cit type="example">
            <quote>xor iskæsæd æ niftujæni, dænttæ razdæxæntæ fæstæmæ</quote>
            <cit type="translation" xml:lang="ru">
                <q>пусть солнце взойдет с запада, пусть реки повернут обратно</q>
            </cit>
            <cit type="translation" xml:lang="en">
                <q>let the sun rise from the west, let the rivers turn back</q>
            </cit>
            <bibl><ref target="#src_Gurdž._Æduli"/><biblScope>96</biblScope></bibl>
        </cit>
    </cit>
    <cit type="exampleGroup">
        <cit type="example" xml:lang="os-x-digor">
            <usg type="dialect"><lang/></usg>
            <quote>ew læg buduri liǧzmæ raftudta</quote>
            <cit type="translation" xml:lang="ru">
                <q>один человек выбрался на степную равнину</q>
            </cit>
            <cit type="translation" xml:lang="en">
                <q>one man appeared at the steppe flatland</q>
            </cit>
            <bibl><ref target="#src_Диг._сказ."/><biblScope>23</biblScope></bibl>
        </cit>
        <cit type="example">
            <quote>cæwync æmæ æfsæn mæsyg, æysæn galwanyl ærbaftydysty</quote>
            <cit type="translation" xml:lang="ru">
                <q>идут они и попали к железной башне, железному зáмку</q>
            </cit>
            <cit type="translation" xml:lang="en">
                <q>they walk and got to an iron tower, an iron castle</q>
            </cit>
            <bibl><ref target="#src_СОПам."/><biblScope>IV 54</biblScope></bibl>
        </cit>
        <cit type="example" xml:lang="os-x-digor">
            <usg type="dialect"><lang/></usg>
            <quote>baftujuj mæ zærdæ tuxsæni</quote>
            <cit type="translation" xml:lang="ru">
                <q>мое сердце впадает в тревогу</q>
            </cit>
            <cit type="translation" xml:lang="en">
                <q>my heart goes into anxiety</q>
            </cit>
            <bibl><ref target="#src_Bes."/><biblScope>67</biblScope></bibl>
        </cit>
        <cit type="example" xml:lang="os-x-digor">
            <usg type="dialect"><lang/></usg>
            <quote>m’ armi esti ku baftuja, wædta art nikkænʒinan</quote>
            <cit type="translation" xml:lang="ru">
                <q>если мне что-нибудь попадет в руки, мы разведем огонь</q>
            </cit>
            <cit type="translation" xml:lang="en">
                <q>if I get my hands on anything, we'll start a fire</q>
            </cit>
            <bibl><ref target="#src_MSt."/><biblScope>10%l13%l</biblScope></bibl>
        </cit>
        <cit type="example">
            <quote>smax rwāǵy baftyd Būrḱyzg mæ kʼūxy</quote>
            <cit type="translation" xml:lang="ru">
                <q>благодаря вам мне досталась в руки Бурчизг</q>
            </cit>
            <cit type="translation" xml:lang="en">
                <q>thanks to you I got Burchizg into my hands</q>
            </cit>
            <bibl><ref target="#src_СОПам."/><biblScope>IV 50</biblScope></bibl>
        </cit>
        <cit type="example" xml:lang="os-x-digor">
            <usg type="dialect"><lang/></usg>
            <quote>aci æntæstitæ ewguræj dær xwarz kusti færci baftudæncæ sæ k’oxi</quote>
            <cit type="translation" xml:lang="ru">
                <q>все эти успехи достались им целиком благодаря хорошей работе</q>
            </cit>
            <cit type="translation" xml:lang="en">
                <q>all these successes went to them entirely because of good work</q>
            </cit>
            <bibl><ref target="#src_AK"/><biblScope>III 51</biblScope></bibl>
        </cit>
    </cit>
    <cit type="exampleGroup">
        <cit type="example">
            <quote>Sozyryqojæ kæj bakajttam, uj jyl baftæd ævdværæj</quote>
            <cit type="translation" xml:lang="ru">
                <q>за ущерб, который мы нанесли Созруко, пусть ему прибавится всемеро</q>
            </cit>
            <cit type="translation" xml:lang="en">
                <q>let it be added seven times to Sozyryqo for the harm we have caused him</q>
            </cit>
            <bibl><ref target="#src_ОЭп."/><biblScope>31</biblScope></bibl>
        </cit>
        <cit type="example">
            <quote>æz am amælʒynæn æmæ bambiʒynæn, ūmæj jyl cy baftʒæn?</quote>
            <cit type="translation" xml:lang="ru">
                <q>оттого, что я здесь умру и сгнию, что ему прибавится?</q>
            </cit>
            <cit type="translation" xml:lang="en">
                <q>because I am here to die and rot, what will he get?</q>
            </cit>
            <bibl><ref target="#src_ОЭп."/><biblScope>24</biblScope></bibl>
        </cit>
        <cit type="example">
            <quote>wynǵy myl īw k˳yʒ baftydi</quote>
            <cit type="translation" xml:lang="ru">
                <q>на улице одна собака пристала ко мне</q>
            </cit>
            <cit type="translation" xml:lang="en">
                <q>on the street one dog stuck to me</q>
            </cit>
        </cit>
        <cit type="example" xml:lang="os-x-digor">
            <usg type="dialect"><lang/></usg>
            <quote>æftyjgæ nez</quote>
            <cit type="translation" xml:lang="ru">
                <q>заразная („пристающая“) болезнь</q>
            </cit>
            <cit type="translation" xml:lang="en">
                <q>contagious (“sticky”) disease</q>
            </cit>
        </cit>
        <cit type="example" xml:lang="os-x-digor">
            <usg type="dialect"><lang/></usg>
            <quote>æftujgæ nezæj sæjgæmæ mæ ma xæssetæ, kenædta mæbæl baftujʒænæj næz æma fæssæjgæ
                woʒænæn</quote>
            <cit type="translation" xml:lang="ru">
                <q>не несите меня к больному заразной болезнью, нето болезнь ко мне пристанет и я
                    заболею</q>
            </cit>
            <cit type="translation" xml:lang="en">
                <q>do not carry me to a patient with an infectious disease, or the disease will
                    stick to me and I will get sick</q>
            </cit>
            <bibl><ref target="#src_FS"/><biblScope>I 103</biblScope></bibl>
        </cit>
    </cit>
    <re><form xml:lang="os-x-iron" type="lemma"><orth>zærdyl æftyn</orth></form><form
            xml:lang="os-x-digor" type="dialectal"><orth>zærdi
                    æftujun</orth></form><sense><sense><cit type="translation" xml:lang="ru">
                    <q>вспоминаться</q>
                </cit><cit type="translation" xml:lang="en">
                    <q>be remembered</q>
                </cit></sense><sense><cit type="translation" xml:lang="ru">
                    <q>приходить на ум</q>
                </cit><cit type="translation" xml:lang="en">
                    <q>come to mind</q>
                </cit></sense></sense><cit type="exampleGroup">
            <cit type="example" xml:lang="os-x-digor">
                <usg type="dialect"><lang/></usg>
                <quote>æftuwis, mæ xwæræ, mæ zærdi ..., æftujuj mæ zærdi xwærz ʒæbæx mæjroxs æxsævi
                    næ badt</quote>
                <cit type="translation" xml:lang="ru">
                    <q>ты мне вспоминаешься, сестра моя, вспоминается мне очень ясно, как мы сидели
                        в лунную ночь</q>
                </cit>
                <cit type="translation" xml:lang="en">
                    <q>I remember you, my sister, I remember very clearly how we sat on a moonlit
                        night</q>
                </cit>
                <bibl><ref target="#src_Qazb."/><biblScope>40</biblScope></bibl>
            </cit>
            <cit type="example" xml:lang="os-x-digor">
                <usg type="dialect"><lang/></usg>
                <quote>æræftujgæj cidær æ zærdi ... læg ærfestæg æj cʼæx zældi</quote>
                <cit type="translation" xml:lang="ru">
                    <q>вспомнив что-то, человек спешился на зеленой траве</q>
                </cit>
                <cit type="translation" xml:lang="en">
                    <q>having remembered something, the man dismounted on the green grass</q>
                </cit>
                <bibl><ref target="#src_Gurdž._Saxi_ræs."/><biblScope>2</biblScope></bibl>
            </cit>
            <cit type="example" xml:lang="os-x-digor">
                <usg type="dialect"><lang/></usg>
                <quote>æ fidi ibæl isardawuni unaffæ æ zærdi æriftudæj</quote>
                <cit type="translation" xml:lang="ru">
                    <q>ей пришло на ум натравить на него отца</q>
                </cit>
                <cit type="translation" xml:lang="en">
                    <q>it came to her mind to set her father on him</q>
                </cit>
                <bibl><ref target="#src_MSt."/><biblScope>8%l3—4%l</biblScope></bibl>
            </cit>
        </cit></re>
    <re><form xml:lang="os-x-iron" type="lemma"><orth>raft-baft kænyn</orth></form><form
            xml:lang="os-x-digor" type="dialectal"><orth>raftawæ-baftawæ
                kænun</orth></form><sense><cit type="translation" xml:lang="ru">
                <q>метаться из стороны в сторону</q>
            </cit><cit type="translation" xml:lang="en">
                <q>rush from side to side</q>
            </cit></sense><note type="comment" xml:lang="ru">ср. %iraxaw-baxaw kænyn%i
            id.</note><note type="comment" xml:lang="en">cf. %iraxaw-baxaw kænyn%i id.</note><cit
            type="exampleGroup">
            <cit type="example">
                <quote>Qæræm Soltan dær duwwerdæmæ raftawæ-baftawæ kodta</quote>
                <cit type="translation" xml:lang="ru">
                    <q>Крым Солтан метался туда-сюда</q>
                </cit>
                <cit type="translation" xml:lang="en">
                    <q>Krym Soltan rushed back and forth</q>
                </cit>
                <bibl><ref target="#src_СОПам."/><biblScope>II 68</biblScope></bibl>
            </cit>
        </cit></re>
    <re><form type="lemma"><orth>raftyn</orth></form><sense><sense><cit type="translation"
                    xml:lang="ru">
                    <q>сойти на нет</q>
                </cit><cit type="translation" xml:lang="en">
                    <q>come to naught</q>
                </cit></sense><sense><cit type="translation" xml:lang="ru">
                    <q>истощиться</q>
                </cit><cit type="translation" xml:lang="en">
                    <q>deplete</q>
                </cit></sense></sense><cit type="exampleGroup">
            <cit type="example">
                <quote>ysxæc-ysxæc ma bærgæ kæny, fælæ nicwal, jæ tyx raftyd</quote>
                <cit type="translation" xml:lang="ru">
                    <q>он еще тужился, но тщетно, сила его иссякла</q>
                </cit>
                <cit type="translation" xml:lang="en">
                    <q>he was still pushing, but in vain, his strength was exhausted</q>
                </cit>
                <bibl><ref target="#src_СОПам."/><biblScope>IV 40</biblScope></bibl>
            </cit>
            <cit type="example">
                <quote>raftydysty wæzzaw k˳ystæj</quote>
                <cit type="translation" xml:lang="ru">
                    <q>от тяжелой работы они истощились</q>
                </cit>
                <cit type="translation" xml:lang="en">
                    <q>from hard work they are depleted</q>
                </cit>
                <bibl><ref target="#src_Хар._Кадӕг"/><biblScope>34</biblScope></bibl>
            </cit>
        </cit></re>
    <cit type="exampleGroup">
        <cit type="example">
            <quote>kæfync … dyværccygæj; binægtæ sqær kænync „æræftʒystut“, wællægtæ sæm ærʒūrync
                „ne ’ræftʒystæm“</quote>
            <cit type="translation" xml:lang="ru">
                <q>пляшут в два яруса (т. е. одни на плечах других); нижние кричат (верхним): «вы
                    свалитесь»; верхние им говорят: «не свалимся»</q>
            </cit>
            <cit type="translation" xml:lang="en">
                <q>they are dancing at two levels (ones at the shoulders of others); the ones below
                    are shouting (to the ones above): “you will fall”; the ones above tell them: “we
                    won't fall”</q>
            </cit>
            <bibl><ref target="#src_Čerm."/><biblScope>97</biblScope></bibl>
        </cit>
        <cit type="example">
            <quote>rarynḱyn qyzty; qæmpyl nyffældæxt, nyftyd</quote>
            <cit type="translation" xml:lang="ru">
                <q>он заболел в стужу; повалился, упал на солому</q>
            </cit>
            <cit type="translation" xml:lang="en">
                <q>he fell ill in the cold; fell down, fell on the straw</q>
            </cit>
            <bibl><ref target="#src_Niger"/><biblScope>68</biblScope></bibl>
        </cit>
        <cit type="example">
            <quote>nyxasy æftydæj læwwydysty</quote>
            <cit type="translation" xml:lang="ru">
                <q>они лежали повалившись на нихасе</q>
            </cit>
            <cit type="translation" xml:lang="en">
                <q>they were lying at the nihas</q>
            </cit>
            <bibl><ref target="#src_ОТ"/><biblScope>71</biblScope></bibl>
        </cit>
        <cit type="example" xml:lang="os-x-digor">
            <usg type="dialect"><lang/></usg>
            <quote>baftudæj k’os dær doni æxsæni</quote>
            <cit type="translation" xml:lang="ru">
                <q>чаша упала в середину реки</q>
            </cit>
            <cit type="translation" xml:lang="en">
                <q>the bowl fell into the middle of the river</q>
            </cit>
            <bibl><ref target="#src_Bes."/><biblScope>110</biblScope></bibl>
        </cit>
        <cit type="example" xml:lang="os-x-digor">
            <usg type="dialect"><lang/></usg>
            <quote>xor raftudæj</quote>
            <cit type="translation" xml:lang="ru">
                <q>солнце зашло</q>
            </cit>
            <cit type="translation" xml:lang="en">
                <q>the sun went down</q>
            </cit>
        </cit>
        <cit type="example" xml:lang="os-x-digor">
            <usg type="dialect"><lang/></usg>
            <quote>kæd dæ bæxbæl cal ardoi es, wal zildi ærkænaj xor-æftudmæ
                ʒaxan-maxan-bæl...</quote>
            <cit type="translation" xml:lang="ru">
                <q>если ты столько раз обернешься до захода солнца по аду, сколько волос на твоем
                    коне...</q>
            </cit>
            <cit type="translation" xml:lang="en">
                <q>if you turn around in hell before the sun goes down as many times as many hairs
                    your horse has...</q>
            </cit>
            <bibl><ref target="#src_Диг._сказ."/><biblScope>38</biblScope></bibl>
        </cit>
        <cit type="example">
            <quote>xor iskæsæd æ niftujæni, dænttæ razdæxæntæ fæstæmæ</quote>
            <cit type="translation" xml:lang="ru">
                <q>пусть солнце взойдет с запада, пусть реки повернут обратно</q>
            </cit>
            <cit type="translation" xml:lang="en">
                <q>let the sun rise from the west, let the rivers turn back</q>
            </cit>
            <bibl><ref target="#src_Gurdž._Æduli"/><biblScope>96</biblScope></bibl>
        </cit>
    </cit>
    <cit type="exampleGroup">
        <cit type="example" xml:lang="os-x-digor">
            <usg type="dialect"><lang/></usg>
            <quote>ew læg buduri liǧzmæ raftudta</quote>
            <cit type="translation" xml:lang="ru">
                <q>один человек выбрался на степную равнину</q>
            </cit>
            <cit type="translation" xml:lang="en">
                <q>one man appeared at the steppe flatland</q>
            </cit>
            <bibl><ref target="#src_Диг._сказ."/><biblScope>23</biblScope></bibl>
        </cit>
        <cit type="example">
            <quote>cæwync æmæ æfsæn mæsyg, æysæn galwanyl ærbaftydysty</quote>
            <cit type="translation" xml:lang="ru">
                <q>идут они и попали к железной башне, железному зáмку</q>
            </cit>
            <cit type="translation" xml:lang="en">
                <q>they walk and got to an iron tower, an iron castle</q>
            </cit>
            <bibl><ref target="#src_СОПам."/><biblScope>IV 54</biblScope></bibl>
        </cit>
        <cit type="example" xml:lang="os-x-digor">
            <usg type="dialect"><lang/></usg>
            <quote>baftujuj mæ zærdæ tuxsæni</quote>
            <cit type="translation" xml:lang="ru">
                <q>мое сердце впадает в тревогу</q>
            </cit>
            <cit type="translation" xml:lang="en">
                <q>my heart goes into anxiety</q>
            </cit>
            <bibl><ref target="#src_Bes."/><biblScope>67</biblScope></bibl>
        </cit>
        <cit type="example" xml:lang="os-x-digor">
            <usg type="dialect"><lang/></usg>
            <quote>m’ armi esti ku baftuja, wædta art nikkænʒinan</quote>
            <cit type="translation" xml:lang="ru">
                <q>если мне что-нибудь попадет в руки, мы разведем огонь</q>
            </cit>
            <cit type="translation" xml:lang="en">
                <q>if I get my hands on anything, we'll start a fire</q>
            </cit>
            <bibl><ref target="#src_MSt."/><biblScope>10%l13%l</biblScope></bibl>
        </cit>
        <cit type="example">
            <quote>smax rwāǵy baftyd Būrḱyzg mæ kʼūxy</quote>
            <cit type="translation" xml:lang="ru">
                <q>благодаря вам мне досталась в руки Бурчизг</q>
            </cit>
            <cit type="translation" xml:lang="en">
                <q>thanks to you I got Burchizg into my hands</q>
            </cit>
            <bibl><ref target="#src_СОПам."/><biblScope>IV 50</biblScope></bibl>
        </cit>
        <cit type="example" xml:lang="os-x-digor">
            <usg type="dialect"><lang/></usg>
            <quote>aci æntæstitæ ewguræj dær xwarz kusti færci baftudæncæ sæ k’oxi</quote>
            <cit type="translation" xml:lang="ru">
                <q>все эти успехи достались им целиком благодаря хорошей работе</q>
            </cit>
            <cit type="translation" xml:lang="en">
                <q>all these successes went to them entirely because of good work</q>
            </cit>
            <bibl><ref target="#src_AK"/><biblScope>III 51</biblScope></bibl>
        </cit>
    </cit>
    <cit type="exampleGroup">
        <cit type="example">
            <quote>Sozyryqojæ kæj bakajttam, uj jyl baftæd ævdværæj</quote>
            <cit type="translation" xml:lang="ru">
                <q>за ущерб, который мы нанесли Созруко, пусть ему прибавится всемеро</q>
            </cit>
            <cit type="translation" xml:lang="en">
                <q>let it be added seven times to Sozyryqo for the harm we have caused him</q>
            </cit>
            <bibl><ref target="#src_ОЭп."/><biblScope>31</biblScope></bibl>
        </cit>
        <cit type="example">
            <quote>æz am amælʒynæn æmæ bambiʒynæn, ūmæj jyl cy baftʒæn?</quote>
            <cit type="translation" xml:lang="ru">
                <q>оттого, что я здесь умру и сгнию, что ему прибавится?</q>
            </cit>
            <cit type="translation" xml:lang="en">
                <q>because I am here to die and rot, what will he get?</q>
            </cit>
            <bibl><ref target="#src_ОЭп."/><biblScope>24</biblScope></bibl>
        </cit>
        <cit type="example">
            <quote>wynǵy myl īw k˳yʒ baftydi</quote>
            <cit type="translation" xml:lang="ru">
                <q>на улице одна собака пристала ко мне</q>
            </cit>
            <cit type="translation" xml:lang="en">
                <q>on the street one dog stuck to me</q>
            </cit>
        </cit>
        <cit type="example" xml:lang="os-x-digor">
            <usg type="dialect"><lang/></usg>
            <quote>æftyjgæ nez</quote>
            <cit type="translation" xml:lang="ru">
                <q>заразная („пристающая“) болезнь</q>
            </cit>
            <cit type="translation" xml:lang="en">
                <q>contagious (“sticky”) disease</q>
            </cit>
        </cit>
        <cit type="example" xml:lang="os-x-digor">
            <usg type="dialect"><lang/></usg>
            <quote>æftujgæ nezæj sæjgæmæ mæ ma xæssetæ, kenædta mæbæl baftujʒænæj næz æma fæssæjgæ
                woʒænæn</quote>
            <cit type="translation" xml:lang="ru">
                <q>не несите меня к больному заразной болезнью, нето болезнь ко мне пристанет и я
                    заболею</q>
            </cit>
            <cit type="translation" xml:lang="en">
                <q>do not carry me to a patient with an infectious disease, or the disease will
                    stick to me and I will get sick</q>
            </cit>
            <bibl><ref target="#src_FS"/><biblScope>I 103</biblScope></bibl>
        </cit>
    </cit>
    <etym xml:lang="ru">Медиальное соответствие к переходному <ref type="xr" target="#entry_æftawyn"
        /> | %iæftawun%i ‘прибавлять’ и пр. с закономерным чередованием %iaw%i || %iu%i; ср. такие
        пары, как д. %iarawun%i [см. <ref type="xr" target="#entry_arawyn"/>] || %iarujun%i, <ref
            type="xr" target="#entry_æmbawun"/> || %iæmbujun%i. Иронская форма %iæftyn%i
        представляет стяжение из %iæftyjyn%i.%n<ref type="xr"/>Вс. Миллер. Gr. 65.</etym>
    <etym xml:lang="en">The middle voice counterpart to transitive <ref type="xr"
            target="#entry_æftawyn"/> | %iæftawun%i ‘increase’ etc. with regular alternation %iaw%i
        || %iu%i; cf. such pairs as Digor %iarawun%i [see <ref type="xr" target="#entry_arawyn"/>]
        || %iarujun%i, <ref type="xr" target="#entry_æmbawun"/> || %iæmbujun%i. The Iron form
        %iæftyn%i is a contraction of %iæftyjyn%i.%n<ref type="xr"/>Вс. Миллер. Gr. 65.</etym>
</entry>
