<?xml version="1.0" encoding="UTF-8"?><entry xmlns:my="http://example.com/my" xmlns="http://www.tei-c.org/ns/1.0" xml:id="entry_arǧævnæ" xml:lang="os-x-digor"><form type="lemma"><orth>arǧævnæ</orth><lang/></form><sense><cit type="translation" xml:lang="ru"><q>клещи</q></cit><note type="comment" xml:lang="">; </note><note type="comment" xml:lang="">; </note><cit type="translation" xml:lang="en"><q>pliers</q></cit><note type="comment" xml:lang="">; </note><note type="comment" xml:lang="">; </note></sense><cit type="exampleGroup" corresp="#sense_arǧævnæ." n=""><cit type="example"><quote>alli brigadæmæ dær ǧæwama wa... æmpʼozægi mænkʼæj arǧævnitæ</quote><cit type="translation" xml:lang="ru"><q>every brigade should have... little repair pliers</q></cit><cit type="translation" xml:lang="en"><q/></cit><bibl><ref target="#src_SD"/><biblScope>245%l3%l</biblScope></bibl></cit><cit type="example"><quote>ʒæbokæ æ razmæ, arǧævnæ.....</quote><cit type="translation" xml:lang="ru"><q>перед ним молоток, клещи...</q></cit><cit type="translation" xml:lang="en"><q>before him there is a hammer, pliers...</q></cit><bibl><ref target="#src_AK"/><biblScope>II 32</biblScope></bibl></cit></cit><cit type="exampleGroup" corresp="#sense_." n=""><cit type="example"><quote>alli brigadæmæ dær ǧæwama wa... æmpʼozægi mænkʼæj arǧævnitæ</quote><cit type="translation" xml:lang="ru"><q>every brigade should have... little repair pliers</q></cit><cit type="translation" xml:lang="en"><q/></cit><bibl><ref target="#src_SD"/><biblScope>245%l3%l</biblScope></bibl></cit><cit type="example"><quote>ʒæbokæ æ razmæ, arǧævnæ.....</quote><cit type="translation" xml:lang="ru"><q>перед ним молоток, клещи...</q></cit><cit type="translation" xml:lang="en"><q>before him there is a hammer, pliers...</q></cit><bibl><ref target="#src_AK"/><biblScope>II 32</biblScope></bibl></cit></cit><etym xml:lang="ru">Восходит к %i*agrab(a)na-%i; ср. по образованию д. <xr><ref target="#entry_araznæ"/></xr> ‘руль’ (от %iarazun%i [<xr><ref target="#entry_arazyn"/></xr>] ‘направлять’), д. <xr><ref target="#entry_izaznæ"/></xr> ‘лом’ (от <xr><ref target="#entry_izazun"/></xr>), д. <xr><ref target="#entry_xeznæ"/></xr> ‘пастбище’ (от <xr><ref target="#entry_xezun"/></xr> ‘пасти’), д. <xr><ref target="#entry_færæznæ"/></xr> ‘возможность’ (от %ifærazun%i [<xr><ref target="#entry_færazyn"/></xr>] ‘мочь’) и др. Основа %irǧæv-%i представляет закономерное развитие из %i*grab-%i (%igr%i → %irg%i, ср. <xr><ref target="#entry_cyrǧ"/></xr>), эта же основа налична в и. <xr><ref target="#entry_rǧævyn"/></xr> ‘взваливать (ношу)’, д. %iærǧævun%i ‘схватывать’, ‘попадать в цель’, а также, с другой огласовкой, в <xr><ref target="#entry_ᵆlǧīvyn"/></xr>, %ilqīvyn%i | %iʽlqevun%i ‘сжимать’. Общеиндоевропейская основа %i*ghre(i)bh-%i ‘хватать’, ‘сгребать’ и пр. обильно представлена в индоиранских, славянских, балтийских и германских языках, причем нередко в названиях орудий, например <mentioned xml:lang="sog"><lang/><w>*аγraβan(ʼγrβn)</w><gloss><q>вилы</q></gloss></mentioned><mentioned xml:lang="sog"><w/><gloss><q>щипцы</q></gloss></mentioned>, , <mentioned xml:lang="sa"><lang/><w>grābhá-, grabhana-</w><gloss><q>орудие хватания</q></gloss></mentioned><mentioned xml:lang="sa"><w/><gloss><q>рукоять</q></gloss></mentioned>, , <mentioned xml:lang="ru"><lang/><w>грабли</w></mentioned>, <mentioned xml:lang="lt"><lang/><w>greblȳs</w><gloss><q>грабли</q></gloss></mentioned>, <mentioned xml:lang="ang"><lang/><w>grāp</w><gloss><q>кулак</q></gloss></mentioned><mentioned xml:lang="ang"><w/><gloss><q>коготь</q></gloss></mentioned>, , <mentioned xml:lang="goh"><lang/><w>greifa</w><gloss><q>вилы</q></gloss></mentioned>, <mentioned xml:lang="de"><lang/><w>Griff</w></mentioned>. Дальнейшие соответствия см. под <xr><ref target="#entry_rǧævyn"/></xr> и <xr><ref target="#entry_ᵆlǧīvyn"/></xr>.%n<bibl corresp="#ref_ОЯФ_I"><biblScope>574</biblScope></bibl>.</etym><etym xml:lang="en">Goes back to %i*agrab(a)na-%i; for derivation, cf. <xr><ref target="#entry_araznæ"/></xr> ‘steering wheel’ (from %iarazun%i [<xr><ref target="#entry_arazyn"/></xr>] ‘direct’), Digor <xr><ref target="#entry_izaznæ"/></xr> ‘pinch-bar’ (from <xr><ref target="#entry_izazun"/></xr>), Digor <xr><ref target="#entry_xeznæ"/></xr> ‘pasture’ (from <xr><ref target="#entry_xezun"/></xr> ‘graze’), Digor <xr><ref target="#entry_færæznæ"/></xr> ‘possibility’ (from %ifærazun%i [<xr><ref target="#entry_færazyn"/></xr>] ‘be able’) etc. The stem %irǧæv-%i regularly developed from %i*grab-%i (%igr%i → %irg%i, cf. <xr><ref target="#entry_cyrǧ"/></xr>), the same stem is availaible in Iron <xr><ref target="#entry_rǧævyn"/></xr> ‘load (carry)’, Digor %iærǧævun%i ‘grab’, ‘hit the mark’ and also (with other vocalization) <xr><ref target="#entry_ᵆlǧīvyn"/></xr>, %ilqīvyn%i | %iʽlqevun%i ‘squeeze’. The common Indo-European stem %i*ghre(i)bh-%i ‘grab’, ‘rake’ etc. abundantly represented in Indo-Iranian, Slavic, Baltic and Germanic languages, often in the names of weapons, for example, <mentioned xml:lang="sog"><lang/><w>*аγraβan(ʼγrβn)</w><gloss><q>hayfork</q></gloss></mentioned><mentioned xml:lang="sog"><w/><gloss><q>forceps</q></gloss></mentioned>, , <mentioned xml:lang="sa"><lang/><w>grābhá-, grabhana-</w><gloss><q>grasping tool</q></gloss></mentioned><mentioned xml:lang="sa"><w/><gloss><q>handle</q></gloss></mentioned>, , <mentioned xml:lang="ru"><lang/><w>грабли</w><gloss><q>rake</q></gloss></mentioned>, <mentioned xml:lang="lt"><lang/><w>greblȳs</w><gloss><q>rake</q></gloss></mentioned>, <mentioned xml:lang="ang"><lang/><w>grāp</w><gloss><q>fist</q></gloss></mentioned><mentioned xml:lang="ang"><w/><gloss><q>claw</q></gloss></mentioned>, , <mentioned xml:lang="goh"><lang/><w>greifa</w><gloss><q>hayfork</q></gloss></mentioned>, <mentioned xml:lang="de"><lang/><w>Griff</w></mentioned>. For further correspondences, see <xr><ref target="#entry_rǧævyn"/></xr> and <xr><ref target="#entry_ᵆlǧīvyn"/></xr>.%n<bibl corresp="#ref_ОЯФ_I"><biblScope>574</biblScope></bibl>.</etym></entry>