<?xml version="1.0" encoding="UTF-8"?><entry xmlns="http://www.tei-c.org/ns/1.0" xml:id="entry_boǧurdaq" xml:lang="os-x-digor"><form type="lemma"><orth>boǧurdaq</orth><lang/></form><sense><cit type="translation" xml:lang="ru"><q>глотка</q></cit><cit type="translation" xml:lang="en"><q>pharynx</q></cit></sense><etym xml:lang="ru">Из <mentioned xml:lang="trk"><lang/><w>boǧurdaq</w><gloss><q>горловой хрящ</q></gloss></mentioned> (<bibl corresp="#ref_Радлов"><biblScope>III 1652</biblScope></bibl>).</etym><etym xml:lang="en">From <mentioned xml:lang="trk"><lang/><w>boǧurdaq</w><gloss><q>guttural cartilage</q></gloss></mentioned> (<bibl corresp="#ref_Радлов"><biblScope>III 1652</biblScope></bibl>).</etym></entry>