<?xml version="1.0" encoding="UTF-8"?><entry xmlns="http://www.tei-c.org/ns/1.0" xml:id="entry_ʒatma" xml:lang="os-x-digor"><form type="lemma"><orth>ʒatma</orth></form><sense><sense><cit type="translation" xml:lang="ru"><q>крыльцо</q></cit><cit type="translation" xml:lang="en"><q>doorstep</q></cit></sense><sense><cit type="translation" xml:lang="ru"><q>навес</q></cit><cit type="translation" xml:lang="en"><q>hovel</q></cit></sense><sense><cit type="translation" xml:lang="ru"><q>балкон</q></cit><cit type="translation" xml:lang="en"><q>balcony</q></cit></sense></sense><cit type="exampleGroup" corresp="#sense_ʒatma." n=""><cit type="example" xml:lang="os-x-digor"><usg type="dialect"><lang/></usg><quote>wælæmæ ma sæ ʒatmamæ iskænetæ</quote><cit type="translation" xml:lang="ru"><q>проводите их наверх на балкон</q></cit><cit type="translation" xml:lang="en"><q>take them upstairs to the balcony</q></cit><bibl><ref target="#src_Диг._сказ."/><biblScope>24</biblScope></bibl></cit><cit type="example" xml:lang="os-x-digor"><usg type="dialect"><lang/></usg><quote>congoj... ragæpp lasta ʒatmaj særæj æma wajun bajdædta</quote><cit type="translation" xml:lang="ru"><q>безрукий спрыгнул с высоты балкона и бросился бежать</q></cit><cit type="translation" xml:lang="en"><q>the armless one jumped from the balcony and started to run</q></cit><bibl><ref target="#src_Диг._сказ."/><biblScope>24</biblScope></bibl></cit><cit type="example" xml:lang="os-x-digor"><usg type="dialect"><lang/></usg><quote>æ ʒonæǧ nivvardta ʒatmaj buni</quote><cit type="translation" xml:lang="ru"><q>поставил сани под навесом</q></cit><cit type="translation" xml:lang="en"><q>he put the sled under the shed</q></cit><bibl><ref target="#src_AK"/><biblScope>II 38</biblScope></bibl></cit></cit><cit type="exampleGroup" corresp="#sense_." n=""><cit type="example" xml:lang="os-x-digor"><usg type="dialect"><lang/></usg><quote>wælæmæ ma sæ ʒatmamæ iskænetæ</quote><cit type="translation" xml:lang="ru"><q>проводите их наверх на балкон</q></cit><cit type="translation" xml:lang="en"><q>take them upstairs to the balcony</q></cit><bibl><ref target="#src_Диг._сказ."/><biblScope>24</biblScope></bibl></cit><cit type="example" xml:lang="os-x-digor"><usg type="dialect"><lang/></usg><quote>congoj... ragæpp lasta ʒatmaj særæj æma wajun bajdædta</quote><cit type="translation" xml:lang="ru"><q>безрукий спрыгнул с высоты балкона и бросился бежать</q></cit><cit type="translation" xml:lang="en"><q>the armless one jumped from the balcony and started to run</q></cit><bibl><ref target="#src_Диг._сказ."/><biblScope>24</biblScope></bibl></cit><cit type="example" xml:lang="os-x-digor"><usg type="dialect"><lang/></usg><quote>æ ʒonæǧ nivvardta ʒatmaj buni</quote><cit type="translation" xml:lang="ru"><q>поставил сани под навесом</q></cit><cit type="translation" xml:lang="en"><q>he put the sled under the shed</q></cit><bibl><ref target="#src_AK"/><biblScope>II 38</biblScope></bibl></cit></cit><etym xml:lang="ru">Из. <mentioned xml:lang="trk"><lang/><w>čatma</w><gloss><q>шалаш</q></gloss></mentioned> (от <mentioned xml:lang="trk"><lang/><w>čatmaq</w><gloss><q>строить</q></gloss></mentioned><mentioned xml:lang="trk"><w/><gloss><q>сооружать</q></gloss></mentioned>, ). Ср. <mentioned xml:lang="krc-x-balkar"><lang/><w>ʒatma</w></mentioned><mentioned xml:lang="krc-x-balkar"><w>zatma</w><gloss><q>навес</q></gloss></mentioned>, <mentioned xml:lang="krc-x-balkar"><w/><gloss><q>балкон</q></gloss></mentioned>, .</etym><etym xml:lang="en">From <mentioned xml:lang="trk"><lang/><w>čatma</w><gloss><q>tent</q></gloss></mentioned> (from <mentioned xml:lang="trk"><lang/><w>čatmaq</w><gloss><q>build</q></gloss></mentioned><mentioned xml:lang="trk"><w/><gloss><q>erect</q></gloss></mentioned>, ). Cf. <mentioned xml:lang="krc-x-balkar"><lang/><w>ʒatma</w></mentioned><mentioned xml:lang="krc-x-balkar"><w>zatma</w><gloss><q>hovel</q></gloss></mentioned>, <mentioned xml:lang="krc-x-balkar"><w/><gloss><q>balcony</q></gloss></mentioned>, .</etym></entry>