<?xml version="1.0" encoding="UTF-8"?><entry xmlns:my="http://example.com/my" xmlns="http://www.tei-c.org/ns/1.0" xml:id="entry_cærgæs" xml:lang="os"><form type="lemma"><orth>cærgæs</orth></form><sense><cit type="translation" xml:lang="ru"><q>орел</q></cit><cit type="translation" xml:lang="en"><q>eagle</q></cit></sense><cit type="exampleGroup" corresp="#sense_cærgæs." n=""><cit type="example"><quote>atæxyn næ wyd jæ særty cærgæsæn jæ bon</quote><cit type="translation" xml:lang="ru"><q>орел не в силах был перелететь через то (море)</q></cit><cit type="translation" xml:lang="en"><q>the eagle could not fly over that (sea)</q></cit><bibl><ref target="#src_Коста"/><biblScope>106</biblScope></bibl></cit><cit type="example" xml:lang="os-x-digor"><usg type="dialect"><lang/></usg><quote>æ særtī ew ustur cærgæs ærbataxtæj</quote><cit type="translation" xml:lang="ru"><q>над ним пролетел один большой орел</q></cit><cit type="translation" xml:lang="en"><q>one big eagle flew over it</q></cit><bibl><ref target="#src_СОПам."/><biblScope>II 11</biblScope></bibl></cit><cit type="example" xml:lang="os-x-digor"><usg type="dialect"><lang/></usg><quote>wæx, ku wajdæ mæ buzurtæ, istæxinæ cærgæsaw</quote><cit type="translation" xml:lang="ru"><q>о, когда б иметь мне крылья, я взлетел бы как орел</q></cit><cit type="translation" xml:lang="en"><q>oh, if I had wings, I would fly like an eagle</q></cit><bibl><ref target="#src_Iræf"/><biblScope>7</biblScope></bibl></cit></cit><cit type="exampleGroup" corresp="#sense_." n=""><cit type="example"><quote>atæxyn næ wyd jæ særty cærgæsæn jæ bon</quote><cit type="translation" xml:lang="ru"><q>орел не в силах был перелететь через то (море)</q></cit><cit type="translation" xml:lang="en"><q>the eagle could not fly over that (sea)</q></cit><bibl><ref target="#src_Коста"/><biblScope>106</biblScope></bibl></cit><cit type="example" xml:lang="os-x-digor"><usg type="dialect"><lang/></usg><quote>æ særtī ew ustur cærgæs ærbataxtæj</quote><cit type="translation" xml:lang="ru"><q>над ним пролетел один большой орел</q></cit><cit type="translation" xml:lang="en"><q>one big eagle flew over it</q></cit><bibl><ref target="#src_СОПам."/><biblScope>II 11</biblScope></bibl></cit><cit type="example" xml:lang="os-x-digor"><usg type="dialect"><lang/></usg><quote>wæx, ku wajdæ mæ buzurtæ, istæxinæ cærgæsaw</quote><cit type="translation" xml:lang="ru"><q>о, когда б иметь мне крылья, я взлетел бы как орел</q></cit><cit type="translation" xml:lang="en"><q>oh, if I had wings, I would fly like an eagle</q></cit><bibl><ref target="#src_Iræf"/><biblScope>7</biblScope></bibl></cit></cit><etym xml:lang="ru">Иранское слово. Ближайшую параллель находим в <mentioned xml:lang="sog"><lang/><w>*čarkas(črks)</w><gloss><q>хищная птица</q></gloss></mentioned>. Исходная форма *%ikarkāsa%i-, буквально „куроед“, ср. <mentioned xml:lang="ae"><lang/><w>kahrkāsa-</w></mentioned>, <mentioned xml:lang="pal"><lang/><w>karkās-</w></mentioned>, <mentioned xml:lang="fa"><lang/><w>kargās-</w><gloss><q>коршун</q></gloss></mentioned>, <mentioned xml:lang="ydg"><lang/><w>karγəz</w><gloss><q>орел</q></gloss></mentioned> (<bibl corresp="#ref_Morgenstierne._IIFL"><biblScope>II 218</biblScope></bibl>). Из скифо-согдийского идут <mentioned xml:lang="mns"><lang/><w>šārkeś</w></mentioned>, <mentioned xml:lang="udm"><lang/><w>ǯuges</w><gloss><q>орел</q></gloss></mentioned>.%n~ <bibl corresp="#ref_Вс._Миллер._Gr."><biblScope>8</biblScope></bibl>. — <bibl corresp="#ref_Bailey._Asica"><biblScope>8</biblScope></bibl>; <bibl corresp="#ref_Bailey._Asica._Suppl."><biblScope>205</biblScope></bibl>. — <bibl corresp="#ref_ОЯФ_I"><biblScope>50</biblScope></bibl>.</etym><etym xml:lang="en">An Iranian word. The closest parallel is found in <mentioned xml:lang="sog"><lang/><w>*čarkas(črks)</w><gloss><q>bird of prey</q></gloss></mentioned>. The initial form is *%ikarkāsa%i-, literally „chicken eater“, cf. <mentioned xml:lang="ae"><lang/><w>kahrkāsa-</w></mentioned>, <mentioned xml:lang="pal"><lang/><w>karkās-</w></mentioned>, <mentioned xml:lang="fa"><lang/><w>kargās-</w><gloss><q>kite</q></gloss></mentioned>, <mentioned xml:lang="ydg"><lang/><w>karγəz</w><gloss><q>eagle</q></gloss></mentioned> (<bibl corresp="#ref_Morgenstierne._IIFL"><biblScope>II 218</biblScope></bibl>). The following words come from Scythian-Sogdian: <mentioned xml:lang="mns"><lang/><w>šārkeś</w></mentioned>, <mentioned xml:lang="udm"><lang/><w>ǯuges</w><gloss><q>eagle</q></gloss></mentioned>.%n~ <bibl corresp="#ref_Вс._Миллер._Gr."><biblScope>8</biblScope></bibl>. — <bibl corresp="#ref_Bailey._Asica"><biblScope>8</biblScope></bibl>; <bibl corresp="#ref_Bailey._Asica._Suppl."><biblScope>205</biblScope></bibl>. — <bibl corresp="#ref_ОЯФ_I"><biblScope>50</biblScope></bibl>.</etym></entry>