<?xml version="1.0" encoding="UTF-8"?><entry xmlns:my="http://example.com/my" xmlns="http://www.tei-c.org/ns/1.0" xml:id="entry_bylamyq" xml:lang="os"><form xml:lang="os-x-iron" type="lemma"><orth>bylamyq</orth></form><form xml:lang="os-x-digor" type="dialectal"><orth>bulamuq</orth></form><sense><cit type="translation" xml:lang="ru"><q>мучная болтушка</q></cit><cit type="translation" xml:lang="en"><q>thin flour dough</q></cit></sense><cit type="exampleGroup" corresp="#sense_bylamyq." n=""><cit type="example"><quote>kard felvæsta ʽmæ ralæwwydī tærxony badæg blamyq rīxītyl</quote><cit type="translation" xml:lang="ru"><q>выхватил меч и стал избивать сидящих на совете любителей %sбламыка%s („чьи усы выпачканы в %sбламыке%s“)“</q></cit><cit type="translation" xml:lang="en"><q>[he] drew a sword and began to beat %sblamyk%s lovers sitting at the council ("those whose moustache became dirty because of %sblamyk%s)"</q></cit><bibl><ref target="#src_СОПам."/><biblScope>III 25</biblScope></bibl></cit></cit><cit type="exampleGroup" corresp="#sense_." n=""><cit type="example"><quote>kard felvæsta ʽmæ ralæwwydī tærxony badæg blamyq rīxītyl</quote><cit type="translation" xml:lang="ru"><q>выхватил меч и стал избивать сидящих на совете любителей %sбламыка%s („чьи усы выпачканы в %sбламыке%s“)“</q></cit><cit type="translation" xml:lang="en"><q>[he] drew a sword and began to beat %sblamyk%s lovers sitting at the council ("those whose moustache became dirty because of %sblamyk%s)"</q></cit><bibl><ref target="#src_СОПам."/><biblScope>III 25</biblScope></bibl></cit></cit><etym xml:lang="ru">Из <mentioned xml:lang="trk"><lang/><w>bulamuq</w></mentioned><mentioned xml:lang="trk"><w>bəlaməq</w><gloss><q>жидкая болтушка из муки</q></gloss><note type="comment" xml:lang=""> ()</note><note type="comment" xml:lang=""> ()</note></mentioned>, ; от глагола %ibulamuq%i ‘размешивать’, ‘разбалтывать’.</etym><etym xml:lang="en">From <mentioned xml:lang="trk"><lang/><w>bulamuq</w></mentioned><mentioned xml:lang="trk"><w>bəlaməq</w><gloss><q>liquid flour dough</q></gloss><note type="comment" xml:lang=""> ()</note><note type="comment" xml:lang=""> ()</note></mentioned>, ; from the verb %ibulamuq%i ‘stir’ up, ‘shake up’.</etym></entry>