<?xml version="1.0" encoding="UTF-8"?>
<entry xmlns:functx="http://www.functx.com" xmlns="http://www.tei-c.org/ns/1.0" xml:id="entry_kʼada"
    xml:lang="os">
    <form type="lemma"><orth>kʼada</orth></form>
    <sense n="1" xml:id="sense_kʼada.1"><sense><cit type="translation" xml:lang="ru">
                <q>маленькая речка</q>
            </cit><cit type="translation" xml:lang="en">
                <q>small river</q>
            </cit></sense><sense><cit type="translation" xml:lang="ru">
                <q>ручей</q>
            </cit><cit type="translation" xml:lang="en">
                <q>brook</q>
            </cit></sense></sense>
    <sense n="2" xml:id="sense_kʼada.2"><cit type="translation" xml:lang="ru">
            <q>мельница на малой воде, на малой речке</q>
        </cit><note type="comment" xml:lang=""> ()</note><note type="comment" xml:lang="">
            ()</note><cit type="translation" xml:lang="en">
            <q>small river mill</q>
        </cit><note type="comment" xml:lang=""> ()</note><note type="comment" xml:lang="">
        ()</note></sense>
    <cit type="exampleGroup">
        <cit type="example">
            <quote>Styr Lewaxi kʼadajy as k˳y wydi...</quote>
            <cit type="translation" xml:lang="ru">
                <q>когда Большая Лиахва была величиной c ручей...</q>
            </cit>
            <cit type="translation" xml:lang="en">
                <q>when the Great Liahwa had the size of a brook...</q>
            </cit>
            <bibl><ref target="#src_ЮОПам."/><biblScope>III 169</biblScope></bibl>
        </cit>
        <cit type="example">
            <quote>ivyld kʼadajaw</quote>
            <cit type="translation" xml:lang="ru">
                <q>как разлившаяся река</q>
            </cit>
            <cit type="translation" xml:lang="en">
                <q>like a flooded river</q>
            </cit>
            <bibl><ref target="#src_Čerm."/><biblScope>118</biblScope></bibl>
        </cit>
    </cit>
    <cit type="exampleGroup">
        <cit type="example" xml:lang="os-x-digor">
            <usg type="dialect"><lang/></usg>
            <quote>es Iræfi sakʼadæxtæbæl kʼadatæ, fal ku raivuluj, wædta sæ nimpursuj ma sæ
                fællasuj</quote>
            <cit type="translation" xml:lang="ru">
                <q>есть на островах реки Ираф мельницы, но когда она разливается, то валит и сносит
                    их</q>
            </cit>
            <cit type="translation" xml:lang="en">
                <q>there are mills on the islands of the Iraf river, but when it floods, it knocks
                    them down and demolishes them</q>
            </cit>
            <bibl><ref target="#src_Iræf"/><biblScope>125</biblScope></bibl>
        </cit>
        <cit type="example" xml:lang="os-x-digor">
            <usg type="dialect"><lang/></usg>
            <quote>mægur xwænxag æxecæn kʼada basaʒuj</quote>
            <cit type="translation" xml:lang="ru">
                <q>бедный горец сколачивает себе мельницу</q>
            </cit>
            <cit type="translation" xml:lang="en">
                <q>a poor highlander makes a mill for himself</q>
            </cit>
            <bibl><ref target="#src_Iræf"/><biblScope>125</biblScope></bibl>
        </cit>
    </cit>
    <cit type="exampleGroup">
        <cit type="example">
            <quote>Styr Lewaxi kʼadajy as k˳y wydi...</quote>
            <cit type="translation" xml:lang="ru">
                <q>когда Большая Лиахва была величиной c ручей...</q>
            </cit>
            <cit type="translation" xml:lang="en">
                <q>when the Great Liahwa had the size of a brook...</q>
            </cit>
            <bibl><ref target="#src_ЮОПам."/><biblScope>III 169</biblScope></bibl>
        </cit>
        <cit type="example">
            <quote>ivyld kʼadajaw</quote>
            <cit type="translation" xml:lang="ru">
                <q>как разлившаяся река</q>
            </cit>
            <cit type="translation" xml:lang="en">
                <q>like a flooded river</q>
            </cit>
            <bibl><ref target="#src_Čerm."/><biblScope>118</biblScope></bibl>
        </cit>
    </cit>
    <cit type="exampleGroup">
        <cit type="example" xml:lang="os-x-digor">
            <usg type="dialect"><lang/></usg>
            <quote>es Iræfi sakʼadæxtæbæl kʼadatæ, fal ku raivuluj, wædta sæ nimpursuj ma sæ
                fællasuj</quote>
            <cit type="translation" xml:lang="ru">
                <q>есть на островах реки Ираф мельницы, но когда она разливается, то валит и сносит
                    их</q>
            </cit>
            <cit type="translation" xml:lang="en">
                <q>there are mills on the islands of the Iraf river, but when it floods, it knocks
                    them down and demolishes them</q>
            </cit>
            <bibl><ref target="#src_Iræf"/><biblScope>125</biblScope></bibl>
        </cit>
        <cit type="example" xml:lang="os-x-digor">
            <usg type="dialect"><lang/></usg>
            <quote>mægur xwænxag æxecæn kʼada basaʒuj</quote>
            <cit type="translation" xml:lang="ru">
                <q>бедный горец сколачивает себе мельницу</q>
            </cit>
            <cit type="translation" xml:lang="en">
                <q>a poor highlander makes a mill for himself</q>
            </cit>
            <bibl><ref target="#src_Iræf"/><biblScope>125</biblScope></bibl>
        </cit>
    </cit>
    <etym xml:lang="ru">Из <mentioned xml:lang="ccs"><lang/><w>k’ad-,
                k’od-</w><gloss><q>ручей</q></gloss></mentioned><mentioned xml:lang="ccs"
                    ><w/><gloss><q>речка</q></gloss></mentioned>, ; ср. <mentioned xml:lang="ka"
                ><lang/><w>na-k’ad-uli, na-k’adi</w><gloss><q>ручей</q></gloss></mentioned>,
            <mentioned xml:lang="ka-x-imer"><lang/><w>kʼodis cʼiskvili</w><note type="comment"
                xml:lang=""> ()</note><note type="comment" xml:lang=""> ()</note><gloss><q>мельница
                    на малой воде</q></gloss></mentioned> (<bibl><ref target="#ref_Беридзе"
        /></bibl>).</etym>
    <etym xml:lang="en">From <mentioned xml:lang="ccs"><lang/><w>k’ad-,
                k’od-</w><gloss><q>brook</q></gloss></mentioned><mentioned xml:lang="ccs"
                    ><w/><gloss><q>river</q></gloss></mentioned>, ; cf. <mentioned xml:lang="ka"
                ><lang/><w>na-k’ad-uli, na-k’adi</w><gloss><q>ручей</q></gloss></mentioned>,
            <mentioned xml:lang="ka-x-imer"><lang/><w>kʼodis cʼiskvili</w><note type="comment"
                xml:lang=""> ()</note><note type="comment" xml:lang=""> ()</note><gloss><q>small
                    water mill</q></gloss></mentioned> (<bibl><ref target="#ref_Беридзе"
        /></bibl>).</etym>
</entry>
