<?xml version="1.0" encoding="UTF-8"?><entry xmlns="http://www.tei-c.org/ns/1.0" xml:id="entry_dojny" xml:lang="os"><form xml:lang="os-x-iron" type="lemma"><orth>dojny</orth></form><form xml:lang="os-x-digor" type="dialectal"><orth>ædonug</orth></form><sense><cit type="translation" xml:lang="ru"><q>жажда</q></cit><cit type="translation" xml:lang="en"><q>thirst</q></cit></sense><re><form type="lemma"><orth>dojny kænyn</orth></form><sense><cit type="translation" xml:lang="ru"><q>испытывать жажду</q></cit><cit type="translation" xml:lang="en"><q>suffer thirst</q></cit></sense></re><cit type="exampleGroup" corresp="#sense_dojny." n=""><cit type="example"><quote>dojnyjæ k˳y mælyn</quote><cit type="translation" xml:lang="ru"><q>ведь я умираю от жажды</q></cit><cit type="translation" xml:lang="en"><q>because I'm dying of thirst</q></cit><bibl><ref target="#src_Брит."/><biblScope>64</biblScope></bibl></cit><cit type="example" xml:lang="os-x-digor"><usg type="dialect"><lang/></usg><quote>cawæjnon xæssuj i donmæ i nad-nad je stong, je ʽdonug, æ fællad</quote><cit type="translation" xml:lang="ru"><q>охотник, (спускаясь) по тропинке, несет к реке свой голод, свою жажду, свою усталость</q></cit><cit type="translation" xml:lang="en"><q>the hunter, (going down) along the path, carries his hunger, his thirst, his fatigue to the river</q></cit><bibl><ref target="#src_Iræf"/><biblScope>62</biblScope></bibl></cit></cit><cit type="exampleGroup" corresp="#sense_." n=""><cit type="example"><quote>dojnyjæ k˳y mælyn</quote><cit type="translation" xml:lang="ru"><q>ведь я умираю от жажды</q></cit><cit type="translation" xml:lang="en"><q>because I'm dying of thirst</q></cit><bibl><ref target="#src_Брит."/><biblScope>64</biblScope></bibl></cit><cit type="example" xml:lang="os-x-digor"><usg type="dialect"><lang/></usg><quote>cawæjnon xæssuj i donmæ i nad-nad je stong, je ʽdonug, æ fællad</quote><cit type="translation" xml:lang="ru"><q>охотник, (спускаясь) по тропинке, несет к реке свой голод, свою жажду, свою усталость</q></cit><cit type="translation" xml:lang="en"><q>the hunter, (going down) along the path, carries his hunger, his thirst, his fatigue to the river</q></cit><bibl><ref target="#src_Iræf"/><biblScope>62</biblScope></bibl></cit></cit><etym xml:lang="ru">Производное от <xr><ref target="#entry_don"/></xr> ‘вода’. В отличие от иронского, где форма стертая, в дигорском образование вполне прозрачное: %iæ-don-ug%i, где %iæ%i ---привативная частица, <xr><ref target="#entry_don"/></xr> ‘вода’, а -%iug%i — суффикс, выражающий наделенность чем-либо; буквально „лишенный воды“. Ср. аналогичное образование %iæ-gom-yg%i ‘немой’, буквально „лишенный рта (<xr><ref target="#entry_kom"/></xr>)“ [см. <xr><ref target="#entry_ægomyg"/></xr>]. Для развития значения ср. <mentioned xml:lang="trk"><lang/><w>su-suz</w><note type="comment" xml:lang=""/><note type="comment" xml:lang=""/><gloss><q>безводный</q></gloss></mentioned><mentioned xml:lang="trk"><w/><note type="comment" xml:lang=""/><note type="comment" xml:lang=""/><gloss><q>жаждущий</q></gloss></mentioned>, . В иронском приходится допускать отпадение начального %iæ%i (%iæ-dony%i → %idojny%i). Появление %ij%i перед носовым обычно; ср., например, <mentioned xml:lang="os"><lang/><w>æmbojny</w><note type="comment" xml:lang=""> ()</note><note type="comment" xml:lang=""> ()</note><gloss><q>в один день</q></gloss></mentioned>.</etym><etym xml:lang="en">A derivative from <xr><ref target="#entry_don"/></xr> ‘water’. Unlike Iron, where the form is unclear, in the Digor the derivation is quite transparent: %iæ-don-ug%i, where %iæ%i --- is a privative particle, <xr><ref target="#entry_don"/></xr> is ‘water’, and -%iug%i is a suffix that means endowment with somthing; literally “missing water”. Cf. an analogous derivation %iæ-gom-yg%i ‘mute’, literally “missing mouth (<xr><ref target="#entry_kom"/></xr>)” [see <xr><ref target="#entry_ægomyg"/></xr>]. For the development of the meaning cf. <mentioned xml:lang="trk"><lang/><w>su-suz</w><note type="comment" xml:lang=""/><note type="comment" xml:lang=""/><gloss><q>waterless</q></gloss></mentioned><mentioned xml:lang="trk"><w/><note type="comment" xml:lang=""/><note type="comment" xml:lang=""/><gloss><q>thirsty</q></gloss></mentioned>, . We have to suppose the loss of the initial %iæ%i in Iron (%iæ-dony%i → %idojny%i). The appearance of %ij%i before nasals; cf., for example, <mentioned xml:lang="os"><lang/><w>æmbojny</w><note type="comment" xml:lang=""> ()</note><note type="comment" xml:lang=""> ()</note><gloss><q>in a single day</q></gloss></mentioned>.</etym></entry>