<?xml version="1.0" encoding="UTF-8"?><entry xmlns="http://www.tei-c.org/ns/1.0" xml:id="entry_cʼiwsūr" xml:lang="os"><form xml:lang="os-x-iron" type="lemma"><orth>cʼiwsūr</orth></form><form xml:lang="os-x-digor" type="dialectal"><orth>cʼewsor</orth></form><sense><cit type="translation" xml:lang="ru"><q>коршун</q></cit><cit type="translation" xml:lang="en"><q>black kite</q></cit></sense><cit type="exampleGroup" corresp="#sense_cʼiwsūr." n=""><cit type="example"><quote>о, cʼīwsūr, ma mæm ʒūr!</quote><cit type="translation" xml:lang="ru"><q>о, коршун, не обращайся ко мне!</q></cit><cit type="translation" xml:lang="en"><q>oh black kite, don't call me!</q></cit><bibl><ref target="#src_Коста"/><biblScope>114</biblScope></bibl></cit><cit type="example" xml:lang="os-x-digor"><usg type="dialect"><lang/></usg><quote>cʼewsor ispær-pær kodta</quote><cit type="translation" xml:lang="ru"><q>коршун взмахнул крыльями</q></cit><cit type="translation" xml:lang="en"><q>the kite flapped its wings</q></cit><bibl><ref target="#src_MD"/><biblScope>1936 II 34</biblScope></bibl></cit></cit><cit type="exampleGroup" corresp="#sense_." n=""><cit type="example"><quote>о, cʼīwsūr, ma mæm ʒūr!</quote><cit type="translation" xml:lang="ru"><q>о, коршун, не обращайся ко мне!</q></cit><cit type="translation" xml:lang="en"><q>oh black kite, don't call me!</q></cit><bibl><ref target="#src_Коста"/><biblScope>114</biblScope></bibl></cit><cit type="example" xml:lang="os-x-digor"><usg type="dialect"><lang/></usg><quote>cʼewsor ispær-pær kodta</quote><cit type="translation" xml:lang="ru"><q>коршун взмахнул крыльями</q></cit><cit type="translation" xml:lang="en"><q>the kite flapped its wings</q></cit><bibl><ref target="#src_MD"/><biblScope>1936 II 34</biblScope></bibl></cit></cit><etym xml:lang="ru">Буквально „преследующий птичек“, см. <xr><ref target="#entry_cʼīw"/></xr> и <xr><ref target="#entry_sūryn"/></xr>.</etym><etym xml:lang="en">Literally, “chasing birds”, see <xr><ref target="#entry_cʼīw"/></xr> and <xr><ref target="#entry_sūryn"/></xr>.</etym></entry>