<?xml version="1.0" encoding="UTF-8"?><entry xmlns="http://www.tei-c.org/ns/1.0" xml:id="entry_ægomyg" xml:lang="os"><form xml:lang="os-x-iron" type="lemma"><orth>ægomyg</orth></form><form xml:lang="os-x-digor" type="dialectal"><orth>ægomug</orth></form><sense><sense><cit type="translation" xml:lang="ru"><q>немой</q></cit><cit type="translation" xml:lang="en"><q>dumb</q></cit></sense><sense><cit type="translation" xml:lang="ru"><q>бессловесный</q></cit><cit type="translation" xml:lang="en"><q>mute</q></cit></sense></sense><re><form type="lemma"><orth>ægomyg fos</orth></form><sense><sense><cit type="translation" xml:lang="ru"><q>бессловесный скот</q></cit><cit type="translation" xml:lang="en"><q>dumb cattle</q></cit></sense><sense><cit type="translation" xml:lang="ru"><q>животные</q></cit><cit type="translation" xml:lang="en"><q>animals</q></cit></sense></sense></re><cit type="exampleGroup" corresp="#sense_ægomyg." n=""><cit type="example"><quote>k’˳yrmatæj qūsǧytæ kæny, ægomǵytæj — ʒurǵytæ</quote><cit type="translation" xml:lang="ru"><q>глухих делает слышащими и немых говорящими</q></cit><cit type="translation" xml:lang="en"><q>He even makes the deaf hear and the mute speak</q></cit><bibl><ref target="#src_Марк"/><biblScope>%i7%i 37</biblScope></bibl></cit><cit type="example"><quote>ærbakodtoj jæm ægomyg læǵy</quote><cit type="translation" xml:lang="ru"><q>привели к нему человека немого</q></cit><cit type="translation" xml:lang="en"><q>they brought to him a dumb man</q></cit><bibl><ref target="#src_Матфей"/><biblScope>%i9%i 32</biblScope></bibl></cit><cit type="example" xml:lang="os-x-digor"><usg type="dialect"><lang/></usg><quote>ægomug ædonug sirdtæ imæ sæ kom satæg kænunmæ ærcæwuncæ</quote><cit type="translation" xml:lang="ru"><q>мучимые жаждой бессловесные звери приходят к нему (роднику) прохладить свой рот</q></cit><cit type="translation" xml:lang="en"><q>thirsty dumb beasts come to it (the spring) to cool their mouth</q></cit><bibl><ref target="#src_MD"/><biblScope>1956 VII 56</biblScope></bibl></cit><cit type="example"><quote>ægomug rist kodta zærdæ</quote><cit type="translation" xml:lang="ru"><q>сердце болело немой болью</q></cit><cit type="translation" xml:lang="en"><q>my heart ached with a dumb pain</q></cit><bibl><ref target="#src_Qazb."/><biblScope>61</biblScope></bibl></cit></cit><cit type="exampleGroup" corresp="#sense_." n=""><cit type="example"><quote>k’˳yrmatæj qūsǧytæ kæny, ægomǵytæj — ʒurǵytæ</quote><cit type="translation" xml:lang="ru"><q>глухих делает слышащими и немых говорящими</q></cit><cit type="translation" xml:lang="en"><q>He even makes the deaf hear and the mute speak</q></cit><bibl><ref target="#src_Марк"/><biblScope>%i7%i 37</biblScope></bibl></cit><cit type="example"><quote>ærbakodtoj jæm ægomyg læǵy</quote><cit type="translation" xml:lang="ru"><q>привели к нему человека немого</q></cit><cit type="translation" xml:lang="en"><q>they brought to him a dumb man</q></cit><bibl><ref target="#src_Матфей"/><biblScope>%i9%i 32</biblScope></bibl></cit><cit type="example" xml:lang="os-x-digor"><usg type="dialect"><lang/></usg><quote>ægomug ædonug sirdtæ imæ sæ kom satæg kænunmæ ærcæwuncæ</quote><cit type="translation" xml:lang="ru"><q>мучимые жаждой бессловесные звери приходят к нему (роднику) прохладить свой рот</q></cit><cit type="translation" xml:lang="en"><q>thirsty dumb beasts come to it (the spring) to cool their mouth</q></cit><bibl><ref target="#src_MD"/><biblScope>1956 VII 56</biblScope></bibl></cit><cit type="example"><quote>ægomug rist kodta zærdæ</quote><cit type="translation" xml:lang="ru"><q>сердце болело немой болью</q></cit><cit type="translation" xml:lang="en"><q>my heart ached with a dumb pain</q></cit><bibl><ref target="#src_Qazb."/><biblScope>61</biblScope></bibl></cit></cit><etym xml:lang="ru">Из %iæ-kom-yg%i ‘лишенный рта’ (<xr><ref target="#entry_æ-"/></xr> — негативная частица, <xr><ref target="#entry_kom"/></xr> ʽротʼ, %i-yg%i — суффикс обладания или наделенности чем-нибудь, например %idyk’ax-yg%i ‘двуногий’ и т. п.). Аналогичные по семантической структуре образования: <mentioned xml:lang="fa"><lang/><w>bīzaban</w><gloss><q>немой</q></gloss></mentioned>, буквально „безъязычный“, <mentioned xml:lang=""><lang/><w>mettaza</w></mentioned> id. (от <mentioned xml:lang=""><lang/><w>mot</w><gloss><q>язык</q></gloss></mentioned>), <mentioned xml:lang="ka"><lang/><w>pʼirutʼqvi</w><gloss><q>бессловесное (животное)</q></gloss></mentioned>, буквально „не говорящее ртом“. „Рот“ как синоним „речи“ выступает также в таких выражениях, как д. %ifækkomægi æj%i „он заговорил“ (<bibl corresp="#ref_СОПам."><biblScope>II 29, 70</biblScope></bibl>), <xr><ref target="#entry_komʒog"/></xr> ‘доносчик’ и др. См. <xr><ref target="#entry_kom"/></xr>. Для структуры ср. д. <xr><ref target="#entry_ædonug"/></xr> ‘жажда’.</etym><etym xml:lang="en">From %iæ-kom-yg%i ‘mouthless’ (<xr><ref target="#entry_æ-"/></xr> is a negative particle, <xr><ref target="#entry_kom"/></xr> is ʽmouthʼ, %i-yg%i is the suffix expressing possession or endowment, for instance %idyk’ax-yg%i ‘two-legged’ etc.). Semantically similar derivations are <mentioned xml:lang="fa"><lang/><w>bīzaban</w><gloss><q>mute</q></gloss></mentioned>, namely “tongueless”, <mentioned xml:lang=""><lang/><w>mettaza</w></mentioned> id. (от <mentioned xml:lang=""><lang/><w>mot</w><gloss><q>tongue</q></gloss></mentioned>), <mentioned xml:lang="ka"><lang/><w>pʼirutʼqvi</w><gloss><q>inarticulate (animal)</q></gloss></mentioned>, literally “not speaking with his mouth”. “Mouth” as a synonym for “speech” also appears in such expressions as Digor %ifækkomægi æj%i “he began to speak” (<bibl corresp="#ref_СОПам."><biblScope>II 29, 70</biblScope></bibl>), <xr><ref target="#entry_komʒog"/></xr> ‘informer’ etc. See <xr><ref target="#entry_kom"/></xr>. For the structure cf. <xr><ref target="#entry_ædonug"/></xr> ‘thirst’.</etym><note type="internal">в этимологии есть пример</note></entry>